odoo10_addon_project_members-10.0.1.0.0.99.dev2-nspkg.pth
odoo/addons/project_members/README.rst
odoo/addons/project_members/__init__.py
odoo/addons/project_members/__manifest__.py
odoo/addons/project_members/models/__init__.py
odoo/addons/project_members/models/project.py
odoo/addons/project_members/static/description/icon.png
odoo/addons/project_members/views/project.xml
odoo10_addon_project_members-10.0.1.0.0.99.dev2.dist-info/METADATA
odoo10_addon_project_members-10.0.1.0.0.99.dev2.dist-info/WHEEL
odoo10_addon_project_members-10.0.1.0.0.99.dev2.dist-info/namespace_packages.txt
odoo10_addon_project_members-10.0.1.0.0.99.dev2.dist-info/top_level.txt
odoo10_addon_project_members-10.0.1.0.0.99.dev2.dist-info/RECORD
